{
    "SN1997ab": {
        "name": "SN1997ab",
        "aliases": [
            "SN1997ab"
        ],
        "sources": [
            {
                "name": "Sternberg Astronomical Institute Supernova Light Curve Catalogue",
                "url": "http://dau.itep.ru/sn/node/72",
                "alias": "1",
                "secondary": true
            },
            {
                "name": "VSNET 2001",
                "alias": "2"
            },
            {
                "name": "Asiago Supernova Catalogue",
                "url": "http://graspa.oapd.inaf.it/cgi-bin/sncat.php",
                "alias": "3",
                "secondary": true
            },
            {
                "name": "IAUC 6589",
                "url": "http://www.cbat.eps.harvard.edu/iauc/06500/06589.html",
                "alias": "4"
            },
            {
                "name": "Latest Supernovae",
                "url": "http://www.rochesterastronomy.org/snimages/snredshiftall.html",
                "alias": "5",
                "secondary": true
            },
            {
                "name": "2012A&A...538A.120L",
                "url": "http://adsabs.harvard.edu/abs/2012A&A...538A.120L",
                "bibcode": "2012A&A...538A.120L",
                "alias": "6"
            }
        ],
        "claimedtype": [
            {
                "value": "IIn",
                "source": "3"
            },
            {
                "value": "II P",
                "source": "4,5"
            }
        ],
        "discoverday": "27",
        "discoverer": "Hagen, Reimers",
        "discovermonth": "2",
        "discoveryear": "1997",
        "galdec": "+200424",
        "galra": "095100",
        "host": [
            {
                "value": "A095100+2004",
                "source": "3"
            }
        ],
        "hvel": [
            {
                "value": "3750",
                "source": "3"
            }
        ],
        "lumdist": [
            {
                "value": "54",
                "source": "D"
            }
        ],
        "maxabsmag": "-18",
        "maxappmag": "15.97",
        "maxday": "31",
        "maxmonth": "3",
        "maxyear": "1997",
        "redshift": [
            {
                "value": "0.012",
                "source": "4,5"
            },
            {
                "value": "0.013",
                "source": "6"
            }
        ],
        "sndec": "+20:04:24.0",
        "snra": "09:51:00.40",
        "photometry": [
            {
                "timeunit": "MJD",
                "time": "50506.5",
                "band": "",
                "abmag": "16.2",
                "source": "4,5"
            },
            {
                "timeunit": "MJD",
                "time": "50538.46",
                "band": "V",
                "abmag": "15.97",
                "source": "1,2"
            }
        ]
    }
}