{
    "SN1991F": {
        "name": "SN1991F",
        "aliases": [
            "SN1991F"
        ],
        "sources": [
            {
                "name": "Asiago Supernova Catalogue",
                "url": "http://graspa.oapd.inaf.it/cgi-bin/sncat.php",
                "alias": "1",
                "secondary": true
            },
            {
                "name": "Latest Supernovae",
                "url": "http://www.rochesterastronomy.org/snimages/snredshiftall.html",
                "alias": "2",
                "secondary": true
            },
            {
                "name": "<a href='http://www.cbat.eps.harvard.edu/iauc/05100/05188.html'>IAUC 5188</a>",
                "alias": "3"
            },
            {
                "name": "2012A&A...538A.120L",
                "url": "http://adsabs.harvard.edu/abs/2012A&A...538A.120L",
                "bibcode": "2012A&A...538A.120L",
                "alias": "4"
            }
        ],
        "claimedtype": [
            {
                "type": "Ia P",
                "source": "1"
            },
            {
                "type": "I",
                "source": "2"
            }
        ],
        "discoverday": "9",
        "discoverer": "Jean Mueller",
        "discovermonth": "2",
        "discoveryear": "1991",
        "galdec": "+570701",
        "galra": "105601",
        "host": "NGC 3458",
        "hvel": "1808",
        "lumdist": "26.8948",
        "maxabsmag": "-14.1483",
        "maxappmag": "18",
        "maxday": "9",
        "maxmonth": "2",
        "maxyear": "1991",
        "redshift": "0.006049",
        "sndec": "+57:06:48.0",
        "snra": "10:56:02.2",
        "photometry": [
            {
                "timeunit": "MJD",
                "time": "48296.5",
                "band": "",
                "abmag": "18.0",
                "source": "3,2"
            }
        ]
    }
}